causal_validation/__about__.py
causal_validation/__init__.py
causal_validation/base.py
causal_validation/config.py
causal_validation/data.py
causal_validation/effects.py
causal_validation/models.py
causal_validation/plotters.py
causal_validation/py.typed
causal_validation/simulate.py
causal_validation/testing.py
causal_validation/types.py
causal_validation/weights.py
causal_validation/transforms/__init__.py
causal_validation/transforms/base.py
causal_validation/transforms/noise.py
causal_validation/transforms/parameter.py
causal_validation/transforms/periodic.py
causal_validation/transforms/trends.py
causal_validation/validation/__init__.py
causal_validation/validation/placebo.py
causal_validation/validation/rmspe.py
causal_validation/validation/testing.py
causal_validation-0.0.9.dist-info/METADATA
causal_validation-0.0.9.dist-info/WHEEL
causal_validation-0.0.9.dist-info/licenses/LICENSE
causal_validation-0.0.9.dist-info/licenses/NOTICE
causal_validation-0.0.9.dist-info/RECORD
