Metadata-Version: 2.3
Name: causal_validation
Version: 0.0.9
Summary: A validation framework for causal models.
Author-email: Thomas Pinder <pinthoma@amazon.nl>
License-Expression: MIT
License-File: LICENSE
License-File: NOTICE
Keywords: causal model,machine learning,synthetic data
Classifier: Development Status :: 4 - Beta
Classifier: Programming Language :: Python
Classifier: Programming Language :: Python :: 3.10
Classifier: Programming Language :: Python :: 3.11
Classifier: Programming Language :: Python :: 3.12
Classifier: Programming Language :: Python :: Implementation :: CPython
Classifier: Programming Language :: Python :: Implementation :: PyPy
Requires-Python: <4.0,>=3.10
Requires-Dist: azcausal
Requires-Dist: beartype
Requires-Dist: jaxtyping
Requires-Dist: matplotlib
Requires-Dist: numpy
Requires-Dist: pandas
Requires-Dist: pandera
Requires-Dist: rich
